glovo_mo_ranking/__init__.py
glovo_mo_ranking-0.0.0.dist-info/METADATA
glovo_mo_ranking-0.0.0.dist-info/WHEEL
glovo_mo_ranking-0.0.0.dist-info/top_level.txt
glovo_mo_ranking-0.0.0.dist-info/RECORD
